amc_optimiser/Optuna_run_cx.py
amc_optimiser/Start_Optimiser.py
amc_optimiser/__init__.py
amc_optimiser/amc.ico
amc_optimiser/py.typed
amc_optimiser/worker_messages.py
amc_optimiser-0.1.8.dist-info/METADATA
amc_optimiser-0.1.8.dist-info/WHEEL
amc_optimiser-0.1.8.dist-info/RECORD
