Metadata-Version: 2.4
Name: amc-optimiser
Version: 0.1.8
Summary: Add your description here
Author-email: James Town <jtown@amcconsultants.com>
Requires-Python: >=3.13
Requires-Dist: customtkinter
Requires-Dist: matplotlib
Requires-Dist: numpy
Requires-Dist: optuna
Requires-Dist: optuna-dashboard
Requires-Dist: pandas
Requires-Dist: psutil
Requires-Dist: pywin32
Requires-Dist: xlwings
